abb_robot_client/__init__.py
abb_robot_client/egm.py
abb_robot_client/rws.py
abb_robot_client/rws_aio.py
abb_robot_client/_egm_protobuf/__init__.py
abb_robot_client/_egm_protobuf/egm_pb2.py
abb_robot_client/robotraconteur/__init__.py
abb_robot_client/robotraconteur/__main__.py
abb_robot_client/robotraconteur/abb_robotraconteur_rws_driver.py
abb_robot_client/robotraconteur/experimental.abb_robot.egm.robdef
abb_robot_client/robotraconteur/experimental.abb_robot.rws.robdef
abb_robot_client-0.4.0.dist-info/LICENSE.txt
abb_robot_client-0.4.0.dist-info/METADATA
abb_robot_client-0.4.0.dist-info/WHEEL
abb_robot_client-0.4.0.dist-info/entry_points.txt
abb_robot_client-0.4.0.dist-info/top_level.txt
abb_robot_client-0.4.0.dist-info/RECORD
