Metadata-Version: 2.1
Name: abb_robot_client
Version: 0.4.0
Summary: Python client library to access ABB robots using RWS and EGM
Home-page: https://github.com/johnwason/abb_robot_client
License-File: LICENSE.txt
Requires-Dist: setuptools
Requires-Dist: requests
Requires-Dist: numpy
Requires-Dist: protobuf
Requires-Dist: websocket-client
Provides-Extra: aio
Requires-Dist: httpx ; extra == 'aio'
Requires-Dist: websockets ; extra == 'aio'
Provides-Extra: robotraconteur
Requires-Dist: robotraconteur ; extra == 'robotraconteur'
Requires-Dist: robotraconteurcompanion ; extra == 'robotraconteur'
Requires-Dist: drekar-launch-process ; extra == 'robotraconteur'
Requires-Dist: robotraconteur-abstract-robot ; extra == 'robotraconteur'
Provides-Extra: testing
Requires-Dist: pytest ; extra == 'testing'
Requires-Dist: pytest-asyncio ; extra == 'testing'
